setup.cfg
setup.py
dva/__init__.py
dva/worker.py
dva.egg-info/.DS_Store
dva.egg-info/PKG-INFO
dva.egg-info/SOURCES.txt
dva.egg-info/dependency_links.txt
dva.egg-info/requires.txt
dva.egg-info/top_level.txt
dva/cloud/__init__.py
dva/cloud/base.py
dva/cloud/driver.py
dva/cloud/ec2.py
dva/cloud/openstack_ec2.py
dva/connection/__init__.py
dva/connection/cache.py
dva/connection/contextmanager.py
dva/report/__init__.py
dva/report/aggregate.py
dva/report/bug_main.py
dva/report/jenkins.py
dva/report/main.py
dva/report/result.py
dva/report/summary_main.py
dva/test/__init__.py
dva/test/testcase.py
dva/test/testcase_01_bash_history.py
dva/test/testcase_02_selinux_context.py
dva/test/testcase_03_running_services.py
dva/test/testcase_04_cloud_firstboot.py
dva/test/testcase_05_grub.py
dva/test/testcase_06_inittab.py
dva/test/testcase_07_libc6_xen_conf.py
dva/test/testcase_08_memory.py
dva/test/testcase_09_nameserver.py
dva/test/testcase_10_networking.py
dva/test/testcase_11_package_set.py
dva/test/testcase_12_passwd_group.py
dva/test/testcase_13_resize2fs.py
dva/test/testcase_14_host_details.py
dva/test/testcase_15_rhel_version.py
dva/test/testcase_16_selinux.py
dva/test/testcase_17_shells.py
dva/test/testcase_18_sshd.py
dva/test/testcase_190_cds_hostnames.py
dva/test/testcase_19_rhn_system_id.py
dva/test/testcase_20_auditd.py
dva/test/testcase_21_disk_size_format.py
dva/test/testcase_22_gpg_keys.py
dva/test/testcase_23_syslog.py
dva/test/testcase_24_yum_plugin.py
dva/test/testcase_25_uname.py
dva/test/testcase_26_verify_rpms.py
dva/test/testcase_27_yum_repos.py
dva/test/testcase_28_iptables.py
dva/test/testcase_29_swap_file.py
dva/test/testcase_30_rhn_certificates.py
dva/test/testcase_31_subscription_management.py
dva/test/testcase_32_ephemeral.py
dva/test/testcase_33_userdata.py
dva/test/testcase_34_cpu.py
dva/test/testcase_35_console.py
dva/test/testcase_360_ebs.py
dva/test/testcase_361_ebs_deferred_detach.py
dva/test/testcase_37_sshd_bug923996.py
dva/test/testcase_38_rclocal_checksum.py
dva/test/testcase_39_root_is_locked.py
dva/test/testcase_41_rh_amazon_rhui_client.py
dva/test/testcase_42_ipv6.py
