Metadata-Version: 1.1
Name: dva
Version: 0.6
Summary: dva's validation. again.
Home-page: https://github.com/RedHatQE/dva
Author: dparalen
Author-email: vetrisko@gmail.com
License: GPLv3+
Platform: UNKNOWN
Classifier: License :: OSI Approved :: GNU General Public License v3 or later (GPLv3+)
Classifier: Programming Language :: Python
Classifier: Topic :: Software Development :: Libraries :: Python Modules
Classifier: Operating System :: POSIX
Classifier: Intended Audience :: Developers
Classifier: Development Status :: 4 - Beta
Provides: d
Provides: v
Provides: a
